__init__.py
gr_aggregation/__init__.py
gr_aggregation/aggregation.py
gr_aggregation/borda_count.py
gr_aggregation/completeness.py
gr_aggregation/ranking.py
gr_aggregation/user_items.py
gr_aggregation-0.0.3.dist-info/LICENSE
gr_aggregation-0.0.3.dist-info/METADATA
gr_aggregation-0.0.3.dist-info/WHEEL
gr_aggregation-0.0.3.dist-info/top_level.txt
gr_aggregation-0.0.3.dist-info/RECORD
